cyberstore/__init__.py
cyberstore/database.py
cyberstore/parse.py
cyberstore/expr_db/__init__.py
cyberstore/expr_db/errors.py
cyberstore/expr_db/expr.py
cyberstore/expr_db/qdf.py
cyberstore/expr_db/udf/__init__.py
cyberstore/expr_db/udf/base_udf.py
cyberstore/expr_db/udf/cs_udf.py
cyberstore/expr_db/udf/d_udf.py
cyberstore/expr_db/udf/ind_udf.py
cyberstore/expr_db/udf/ts_udf.py
cyberstore/updater/__init__.py
cyberstore/updater/base.py
cyberstore/updater/updater.py
cyberstore-0.0.1b1.dist-info/METADATA
cyberstore-0.0.1b1.dist-info/WHEEL
cyberstore-0.0.1b1.dist-info/top_level.txt
cyberstore-0.0.1b1.dist-info/RECORD
